mypackage/__init__.py
mypackage/modulo_a.py
mypackage/modulo_b.py
example_package_an_academy_test-0.0.1.dist-info/LICENSE
example_package_an_academy_test-0.0.1.dist-info/METADATA
example_package_an_academy_test-0.0.1.dist-info/WHEEL
example_package_an_academy_test-0.0.1.dist-info/top_level.txt
example_package_an_academy_test-0.0.1.dist-info/RECORD
