Metadata-Version: 2.2
Name: example_package_an_academy_test
Version: 0.0.1
Summary: A small example package
Author-email: Mario Rossi <author@example.com>
License: MIT
Project-URL: Homepage, https://github.com/pypa/sampleproject
Project-URL: Issues, https://github.com/pypa/sampleproject/issues
Classifier: Programming Language :: Python :: 3
Classifier: Operating System :: OS Independent
Requires-Python: >=3.8
License-File: LICENSE
